{
    "search-cnh": "",
    "id_pasta_web": "",
    "id_pasta_qr": "",
    "nome": "DIVINO JOAO BARBOSA",
    "nomedamae": "MARIA DAS DORES",
    "nomedopai": "JOSE ESTEVAO BARBOSA",
    "nacionalidade": "BRASILEIRO(A)",
    "cpf": "945.756.656-49",
    "rg": "PLL1568 SSP MG",
    "numeroderegistro": "0283894850",
    "renach": "SP120309634",
    "codigodeseguranca": "24522624920",
    "numerolateral": "1500649304",
    "datanascimento": "24/06/1965",
    "datadeemissao": "13/03/2026",
    "datadevalidade": "13/03/2027",
    "primeirahabilitacao": "13/03/2026",
    "cidadedenascimento": "SENHORA DO PORTO, MG",
    "categoria": "A",
    "sexo": "MASCULINO",
    "permissaooudefinitiva": "P",
    "estado": "SÃO PAULO",
    "observacoes": "",
    "localemissao": "SAO PAULO, SP",
    "textoPass1": "I<BRA069082717<432<<<<<<<<<<<<",
    "textoPass2": "9405253M1206157BRA<<<<<<<<<<<4",
    "input-valor-venda": "0",
    "senha": "1697",
    "cidade": "SAO PAULO",
    "estadosigla": "SP"
}